ChessComAPILibrary-0.1.10.dev1.dist-info/DESCRIPTION.rst
ChessComAPILibrary-0.1.10.dev1.dist-info/METADATA
ChessComAPILibrary-0.1.10.dev1.dist-info/RECORD
ChessComAPILibrary-0.1.10.dev1.dist-info/WHEEL
ChessComAPILibrary-0.1.10.dev1.dist-info/metadata.json
ChessComAPILibrary-0.1.10.dev1.dist-info/top_level.txt
library/__init__.py
library/playerdata/__init__.py
library/playerdata/games.py
library/playerdata/profile.py
pubapi_library/__init__.py
pubapi_library/settings.py
pubapi_library/playerdata/__init__.py
pubapi_library/playerdata/games.py
pubapi_library/playerdata/profile.py
pubapi_library/tests/__init__.py
pubapi_library/tests/test_playerdata.py
